{
    "FLW3": {
        "flow": {
            "0": {
                "type": "start",
                "next": 199
            },
            "1": {
                "type": "type1",
                "next": -1,
                "param3": 81,
                "param4": 0
            },
            "2": {
                "type": "start",
                "next": 77
            },
            "3": {
                "type": "type1",
                "next": 76,
                "param3": 81,
                "param4": 1
            },
            "4": {
                "type": "start",
                "next": 201
            },
            "5": {
                "type": "type1",
                "next": 21,
                "param3": 81,
                "param4": 9
            },
            "6": {
                "type": "start",
                "next": 73
            },
            "7": {
                "type": "type1",
                "next": -1,
                "param3": 81,
                "param4": 12
            },
            "8": {
                "type": "switch",
                "subType": 6,
                "param2": 26,
                "param3": 3,
                "param4": 2,
                "param5": 0
            },
            "9": {
                "type": "type1",
                "next": -1,
                "param3": 81,
                "param4": 13
            },
            "10": {
                "type": "switch",
                "subType": 6,
                "param2": 39,
                "param3": 3,
                "param4": 2,
                "param5": 2
            },
            "11": {
                "type": "start",
                "next": 12
            },
            "12": {
                "type": "type3",
                "subType": 0,
                "param1": 0,
                "param2": 32,
                "next": 13,
                "param3": 0
            },
            "13": {
                "type": "type3",
                "subType": 1,
                "param1": 9,
                "param2": 0,
                "next": -1,
                "param3": 10
            },
            "14": {
                "type": "type1",
                "next": 17,
                "param3": 81,
                "param4": 10
            },
            "15": {
                "type": "type3",
                "subType": 1,
                "param1": 1,
                "param2": 100,
                "next": 103,
                "param3": 17
            },
            "16": {
                "type": "type3",
                "subType": 2,
                "param1": 8,
                "param2": 257,
                "next": 79,
                "param3": 15
            },
            "17": {
                "type": "type3",
                "subType": 1,
                "param1": 1,
                "param2": 100,
                "next": 18,
                "param3": 17
            },
            "18": {
                "type": "type3",
                "subType": 1,
                "param1": 3,
                "param2": 0,
                "next": 172,
                "param3": 39
            },
            "19": {
                "type": "type3",
                "subType": 0,
                "param1": 0,
                "param2": 1,
                "next": 16,
                "param3": 32
            },
            "20": {
                "type": "type3",
                "subType": 1,
                "param1": 1,
                "param2": 99,
                "next": 106,
                "param3": 50
            },
            "21": {
                "type": "type3",
                "subType": 1,
                "param1": 2,
                "param2": 0,
                "next": 14,
                "param3": 39
            },
            "22": {
                "type": "start",
                "next": 191
            },
            "23": {
                "type": "type1",
                "next": 64,
                "param3": 81,
                "param4": 19
            },
            "24": {
                "type": "type1",
                "next": 146,
                "param3": 81,
                "param4": 20
            },
            "25": {
                "type": "type1",
                "next": 65,
                "param3": 81,
                "param4": 22
            },
            "26": {
                "type": "type1",
                "next": 47,
                "param3": 81,
                "param4": 23
            },
            "27": {
                "type": "type1",
                "next": 50,
                "param3": 81,
                "param4": 24
            },
            "28": {
                "type": "type1",
                "next": 63,
                "param3": 81,
                "param4": 25
            },
            "29": {
                "type": "type1",
                "next": 107,
                "param3": 81,
                "param4": 26
            },
            "30": {
                "type": "type1",
                "next": 52,
                "param3": 81,
                "param4": 28
            },
            "31": {
                "type": "type1",
                "next": 61,
                "param3": 81,
                "param4": 29
            },
            "32": {
                "type": "type1",
                "next": 54,
                "param3": 81,
                "param4": 30
            },
            "33": {
                "type": "type1",
                "next": 68,
                "param3": 81,
                "param4": 31
            },
            "34": {
                "type": "type1",
                "next": 87,
                "param3": 81,
                "param4": 32
            },
            "35": {
                "type": "type1",
                "next": 99,
                "param3": 81,
                "param4": 34
            },
            "36": {
                "type": "type1",
                "next": 57,
                "param3": 81,
                "param4": 35
            },
            "37": {
                "type": "type1",
                "next": 101,
                "param3": 81,
                "param4": 36
            },
            "38": {
                "type": "type1",
                "next": 101,
                "param3": 81,
                "param4": 37
            },
            "39": {
                "type": "type1",
                "next": 101,
                "param3": 81,
                "param4": 38
            },
            "40": {
                "type": "type1",
                "next": 59,
                "param3": 81,
                "param4": 39
            },
            "41": {
                "type": "type1",
                "next": 70,
                "param3": 81,
                "param4": 40
            },
            "42": {
                "type": "type3",
                "subType": 0,
                "param1": 0,
                "param2": 4,
                "next": 43,
                "param3": 32
            },
            "43": {
                "type": "type3",
                "subType": 0,
                "param1": 0,
                "param2": 5,
                "next": 44,
                "param3": 32
            },
            "44": {
                "type": "type3",
                "subType": 0,
                "param1": 0,
                "param2": 6,
                "next": 144,
                "param3": 32
            },
            "45": {
                "type": "type3",
                "subType": 1,
                "param1": 4,
                "param2": 100,
                "next": 24,
                "param3": 16
            },
            "46": {
                "type": "type3",
                "subType": 1,
                "param1": 5,
                "param2": 6,
                "next": 48,
                "param3": 16
            },
            "47": {
                "type": "type3",
                "subType": 1,
                "param1": 6,
                "param2": 5,
                "next": 27,
                "param3": 16
            },
            "48": {
                "type": "type3",
                "subType": 1,
                "param1": 6,
                "param2": 5,
                "next": 26,
                "param3": 17
            },
            "49": {
                "type": "type3",
                "subType": 1,
                "param1": 4,
                "param2": -1,
                "next": 28,
                "param3": 16
            },
            "50": {
                "type": "type3",
                "subType": 1,
                "param1": 4,
                "param2": 100,
                "next": 66,
                "param3": 17
            },
            "51": {
                "type": "type3",
                "subType": 1,
                "param1": 5,
                "param2": 4,
                "next": 110,
                "param3": 50
            },
            "52": {
                "type": "type3",
                "subType": 1,
                "param1": 4,
                "param2": 5,
                "next": 31,
                "param3": 16
            },
            "53": {
                "type": "type3",
                "subType": 1,
                "param1": 4,
                "param2": 0,
                "next": 32,
                "param3": 17
            },
            "54": {
                "type": "type3",
                "subType": 1,
                "param1": 0,
                "param2": 6,
                "next": 147,
                "param3": 16
            },
            "55": {
                "type": "type3",
                "subType": 1,
                "param1": 4,
                "param2": 100,
                "next": 34,
                "param3": 16
            },
            "56": {
                "type": "type3",
                "subType": 1,
                "param1": 5,
                "param2": 4,
                "next": 91,
                "param3": 16
            },
            "57": {
                "type": "switch",
                "subType": 6,
                "param2": 0,
                "param3": 1,
                "param4": 3,
                "param5": 4
            },
            "58": {
                "type": "type3",
                "subType": 1,
                "param1": 6,
                "param2": -1,
                "next": 221,
                "param3": 16
            },
            "59": {
                "type": "type3",
                "subType": 1,
                "param1": 0,
                "param2": 100,
                "next": 41,
                "param3": 16
            },
            "60": {
                "type": "type3",
                "subType": 2,
                "param1": 16,
                "param2": 0,
                "next": 42,
                "param3": 14
            },
            "61": {
                "type": "type3",
                "subType": 2,
                "param1": 11,
                "param2": 0,
                "next": 92,
                "param3": 15
            },
            "62": {
                "type": "type3",
                "subType": 2,
                "param1": 10,
                "param2": 4,
                "next": 56,
                "param3": 14
            },
            "63": {
                "type": "type3",
                "subType": 1,
                "param1": 4,
                "param2": 5,
                "next": 29,
                "param3": 17
            },
            "64": {
                "type": "type3",
                "subType": 1,
                "param1": 10,
                "param2": 0,
                "next": 143,
                "param3": 39
            },
            "65": {
                "type": "type3",
                "subType": 1,
                "param1": 13,
                "param2": 0,
                "next": 46,
                "param3": 39
            },
            "66": {
                "type": "type3",
                "subType": 1,
                "param1": 12,
                "param2": 0,
                "next": 49,
                "param3": 39
            },
            "67": {
                "type": "type3",
                "subType": 1,
                "param1": 18,
                "param2": 0,
                "next": 30,
                "param3": 39
            },
            "68": {
                "type": "type3",
                "subType": 1,
                "param1": 15,
                "param2": 0,
                "next": 55,
                "param3": 39
            },
            "69": {
                "type": "type3",
                "subType": 1,
                "param1": 16,
                "param2": 0,
                "next": 36,
                "param3": 39
            },
            "70": {
                "type": "type3",
                "subType": 1,
                "param1": 18,
                "param2": 0,
                "next": -1,
                "param3": 10
            },
            "71": {
                "type": "start",
                "next": 72
            },
            "72": {
                "type": "type1",
                "next": -1,
                "param3": 81,
                "param4": 41
            },
            "73": {
                "type": "switch",
                "subType": 6,
                "param2": 3,
                "param3": 6,
                "param4": 2,
                "param5": 7
            },
            "74": {
                "type": "type1",
                "next": 75,
                "param3": 81,
                "param4": 18
            },
            "75": {
                "type": "type3",
                "subType": 1,
                "param1": 3,
                "param2": 0,
                "next": 235,
                "param3": 3
            },
            "76": {
                "type": "type1",
                "next": 138,
                "param3": 81,
                "param4": 2
            },
            "77": {
                "type": "type3",
                "subType": 0,
                "param1": 0,
                "param2": 1,
                "next": 15,
                "param3": 32
            },
            "78": {
                "type": "type3",
                "subType": 1,
                "param1": 1,
                "param2": -1,
                "next": 3,
                "param3": 16
            },
            "79": {
                "type": "type3",
                "subType": 2,
                "param1": 17,
                "param2": 100,
                "next": 80,
                "param3": 15
            },
            "80": {
                "type": "type3",
                "subType": 2,
                "param1": 17,
                "param2": 356,
                "next": 181,
                "param3": 14
            },
            "81": {
                "type": "type3",
                "subType": 2,
                "param1": 8,
                "param2": 1,
                "next": 105,
                "param3": 14
            },
            "82": {
                "type": "start",
                "next": 83
            },
            "83": {
                "type": "type1",
                "next": 84,
                "param3": 81,
                "param4": 42
            },
            "84": {
                "type": "type1",
                "next": 85,
                "param3": 81,
                "param4": 43
            },
            "85": {
                "type": "type1",
                "next": -1,
                "param3": 81,
                "param4": 44
            },
            "86": {
                "type": "type1",
                "next": 62,
                "param3": 81,
                "param4": 33
            },
            "87": {
                "type": "type3",
                "subType": 1,
                "param1": 4,
                "param2": 0,
                "next": 86,
                "param3": 17
            },
            "88": {
                "type": "start",
                "next": 89
            },
            "89": {
                "type": "type1",
                "next": -1,
                "param3": 81,
                "param4": 47
            },
            "90": {
                "type": "type3",
                "subType": 1,
                "param1": 19,
                "param2": 0,
                "next": 33,
                "param3": 39
            },
            "91": {
                "type": "type3",
                "subType": 1,
                "param1": 6,
                "param2": 4,
                "next": 98,
                "param3": 17
            },
            "92": {
                "type": "type3",
                "subType": 1,
                "param1": 0,
                "param2": 4,
                "next": 97,
                "param3": 17
            },
            "93": {
                "type": "type3",
                "subType": 1,
                "param1": 12,
                "param2": 0,
                "next": 45,
                "param3": 39
            },
            "94": {
                "type": "type3",
                "subType": 4,
                "param1": 1038,
                "param2": 11776,
                "next": 145,
                "param3": 13
            },
            "95": {
                "type": "type3",
                "subType": 1,
                "param1": 12,
                "param2": 0,
                "next": 96,
                "param3": 39
            },
            "96": {
                "type": "type3",
                "subType": 4,
                "param1": 1035,
                "param2": 12606,
                "next": 25,
                "param3": 13
            },
            "97": {
                "type": "type3",
                "subType": 1,
                "param1": 14,
                "param2": 0,
                "next": 53,
                "param3": 39
            },
            "98": {
                "type": "type3",
                "subType": 1,
                "param1": 18,
                "param2": 0,
                "next": 35,
                "param3": 39
            },
            "99": {
                "type": "type3",
                "subType": 4,
                "param1": 1298,
                "param2": 4352,
                "next": 100,
                "param3": 13
            },
            "100": {
                "type": "type3",
                "subType": 4,
                "param1": 1553,
                "param2": 4096,
                "next": 114,
                "param3": 13
            },
            "101": {
                "type": "type3",
                "subType": 4,
                "param1": 12,
                "param2": -256,
                "next": 207,
                "param3": 13
            },
            "102": {
                "type": "type3",
                "subType": 1,
                "param1": 4,
                "param2": 0,
                "next": 19,
                "param3": 39
            },
            "103": {
                "type": "type3",
                "subType": 1,
                "param1": 100,
                "param2": 1,
                "next": 78,
                "param3": 17
            },
            "104": {
                "type": "type3",
                "subType": 4,
                "param1": 273,
                "param2": 4864,
                "next": 81,
                "param3": 13
            },
            "105": {
                "type": "type3",
                "subType": 1,
                "param1": 1,
                "param2": 0,
                "next": 20,
                "param3": 39
            },
            "106": {
                "type": "type3",
                "subType": 4,
                "param1": 270,
                "param2": 4360,
                "next": 5,
                "param3": 13
            },
            "107": {
                "type": "type3",
                "subType": 1,
                "param1": 17,
                "param2": 0,
                "next": 108,
                "param3": 39
            },
            "108": {
                "type": "type3",
                "subType": 4,
                "param1": 1048,
                "param2": 5644,
                "next": 109,
                "param3": 13
            },
            "109": {
                "type": "type1",
                "next": 51,
                "param3": 81,
                "param4": 27
            },
            "110": {
                "type": "type3",
                "subType": 4,
                "param1": 1296,
                "param2": 3865,
                "next": 111,
                "param3": 13
            },
            "111": {
                "type": "type3",
                "subType": 4,
                "param1": 1552,
                "param2": 2060,
                "next": 67,
                "param3": 13
            },
            "112": {
                "type": "start",
                "next": 117
            },
            "113": {
                "type": "type1",
                "next": 118,
                "param3": 81,
                "param4": 14
            },
            "114": {
                "type": "type3",
                "subType": 1,
                "param1": 0,
                "param2": 5,
                "next": 115,
                "param3": 33
            },
            "115": {
                "type": "type3",
                "subType": 1,
                "param1": 0,
                "param2": 6,
                "next": 116,
                "param3": 33
            },
            "116": {
                "type": "type3",
                "subType": 0,
                "param1": 0,
                "param2": 50,
                "next": 205,
                "param3": 6
            },
            "117": {
                "type": "type3",
                "subType": 1,
                "param1": 26,
                "param2": 0,
                "next": 119,
                "param3": 39
            },
            "118": {
                "type": "type3",
                "subType": 1,
                "param1": -1,
                "param2": 0,
                "next": -1,
                "param3": 39
            },
            "119": {
                "type": "type3",
                "subType": 0,
                "param1": 0,
                "param2": 1,
                "next": 120,
                "param3": 32
            },
            "120": {
                "type": "type3",
                "subType": 1,
                "param1": 1,
                "param2": -1,
                "next": 113,
                "param3": 16
            },
            "121": {
                "type": "start",
                "next": 200
            },
            "122": {
                "type": "type1",
                "next": -1,
                "param3": 81,
                "param4": 48
            },
            "123": {
                "type": "start",
                "next": 208
            },
            "124": {
                "type": "start",
                "next": 209
            },
            "125": {
                "type": "switch",
                "subType": 6,
                "param2": 304,
                "param3": 3,
                "param4": 2,
                "param5": 9
            },
            "126": {
                "type": "type3",
                "subType": 0,
                "param1": 0,
                "param2": 329,
                "next": 148,
                "param3": 0
            },
            "127": {
                "type": "switch",
                "subType": 6,
                "param2": 304,
                "param3": 3,
                "param4": 2,
                "param5": 11
            },
            "128": {
                "type": "type3",
                "subType": 0,
                "param1": 0,
                "param2": 329,
                "next": 150,
                "param3": 0
            },
            "129": {
                "type": "type3",
                "subType": 1,
                "param1": 65,
                "param2": 0,
                "next": 156,
                "param3": 3
            },
            "130": {
                "type": "switch",
                "subType": 6,
                "param2": 65,
                "param3": 6,
                "param4": 2,
                "param5": 13
            },
            "131": {
                "type": "switch",
                "subType": 6,
                "param2": 545,
                "param3": 3,
                "param4": 2,
                "param5": 15
            },
            "132": {
                "type": "switch",
                "subType": 6,
                "param2": 548,
                "param3": 3,
                "param4": 2,
                "param5": 17
            },
            "133": {
                "type": "switch",
                "subType": 6,
                "param2": 551,
                "param3": 3,
                "param4": 2,
                "param5": 19
            },
            "134": {
                "type": "type3",
                "subType": 1,
                "param1": 65,
                "param2": 0,
                "next": 159,
                "param3": 2
            },
            "135": {
                "type": "type1",
                "next": 170,
                "param3": 81,
                "param4": 7
            },
            "136": {
                "type": "type1",
                "next": 140,
                "param3": 81,
                "param4": 6
            },
            "137": {
                "type": "type3",
                "subType": 4,
                "param1": 260,
                "param2": 528,
                "next": 135,
                "param3": 13
            },
            "138": {
                "type": "type3",
                "subType": 1,
                "param1": 22,
                "param2": 0,
                "next": 202,
                "param3": 39
            },
            "139": {
                "type": "type3",
                "subType": 1,
                "param1": 24,
                "param2": 0,
                "next": 141,
                "param3": 39
            },
            "140": {
                "type": "type3",
                "subType": 1,
                "param1": 3,
                "param2": -1,
                "next": -1,
                "param3": 42
            },
            "141": {
                "type": "type3",
                "subType": 4,
                "param1": 268,
                "param2": 5376,
                "next": 136,
                "param3": 13
            },
            "142": {
                "type": "type3",
                "subType": 2,
                "param1": 5,
                "param2": 4,
                "next": 93,
                "param3": 14
            },
            "143": {
                "type": "type3",
                "subType": 4,
                "param1": 17,
                "param2": 4864,
                "next": 60,
                "param3": 13
            },
            "144": {
                "type": "type3",
                "subType": 1,
                "param1": 9,
                "param2": 0,
                "next": 142,
                "param3": 39
            },
            "145": {
                "type": "type1",
                "next": 95,
                "param3": 81,
                "param4": 21
            },
            "146": {
                "type": "type3",
                "subType": 1,
                "param1": 9,
                "param2": 0,
                "next": 94,
                "param3": 39
            },
            "147": {
                "type": "type3",
                "subType": 4,
                "param1": 13,
                "param2": 4103,
                "next": 90,
                "param3": 13
            },
            "148": {
                "type": "switch",
                "subType": 6,
                "param2": 373,
                "param3": 3,
                "param4": 2,
                "param5": 21
            },
            "149": {
                "type": "type3",
                "subType": 0,
                "param1": 0,
                "param2": 375,
                "next": 154,
                "param3": 0
            },
            "150": {
                "type": "switch",
                "subType": 6,
                "param2": 373,
                "param3": 3,
                "param4": 2,
                "param5": 23
            },
            "151": {
                "type": "type3",
                "subType": 0,
                "param1": 0,
                "param2": 375,
                "next": 152,
                "param3": 0
            },
            "152": {
                "type": "switch",
                "subType": 6,
                "param2": 472,
                "param3": 3,
                "param4": 2,
                "param5": 25
            },
            "153": {
                "type": "type3",
                "subType": 0,
                "param1": 0,
                "param2": 473,
                "next": 195,
                "param3": 0
            },
            "154": {
                "type": "switch",
                "subType": 6,
                "param2": 472,
                "param3": 3,
                "param4": 2,
                "param5": 27
            },
            "155": {
                "type": "type3",
                "subType": 0,
                "param1": 0,
                "param2": 473,
                "next": 196,
                "param3": 0
            },
            "156": {
                "type": "switch",
                "subType": 6,
                "param2": 389,
                "param3": 3,
                "param4": 2,
                "param5": 29
            },
            "157": {
                "type": "type3",
                "subType": 0,
                "param1": 0,
                "param2": 390,
                "next": 158,
                "param3": 0
            },
            "158": {
                "type": "switch",
                "subType": 6,
                "param2": 392,
                "param3": 3,
                "param4": 2,
                "param5": 31
            },
            "159": {
                "type": "switch",
                "subType": 6,
                "param2": 554,
                "param3": 3,
                "param4": 2,
                "param5": 33
            },
            "160": {
                "type": "type3",
                "subType": 0,
                "param1": 0,
                "param2": 558,
                "next": 162,
                "param3": 0
            },
            "161": {
                "type": "switch",
                "subType": 6,
                "param2": 554,
                "param3": 3,
                "param4": 2,
                "param5": 35
            },
            "162": {
                "type": "type3",
                "subType": 0,
                "param1": 0,
                "param2": 559,
                "next": 166,
                "param3": 0
            },
            "163": {
                "type": "type3",
                "subType": 0,
                "param1": 0,
                "param2": 558,
                "next": 164,
                "param3": 0
            },
            "164": {
                "type": "type3",
                "subType": 0,
                "param1": 0,
                "param2": 559,
                "next": 165,
                "param3": 0
            },
            "165": {
                "type": "switch",
                "subType": 6,
                "param2": 581,
                "param3": 3,
                "param4": 2,
                "param5": 37
            },
            "166": {
                "type": "switch",
                "subType": 6,
                "param2": 635,
                "param3": 3,
                "param4": 2,
                "param5": 39
            },
            "167": {
                "type": "type3",
                "subType": 0,
                "param1": 0,
                "param2": 638,
                "next": 182,
                "param3": 0
            },
            "168": {
                "type": "switch",
                "subType": 6,
                "param2": 635,
                "param3": 3,
                "param4": 2,
                "param5": 41
            },
            "169": {
                "type": "type3",
                "subType": 0,
                "param1": 0,
                "param2": 638,
                "next": 177,
                "param3": 0
            },
            "170": {
                "type": "type3",
                "subType": 1,
                "param1": 25,
                "param2": 0,
                "next": 171,
                "param3": 39
            },
            "171": {
                "type": "type1",
                "next": 139,
                "param3": 81,
                "param4": 8
            },
            "172": {
                "type": "type3",
                "subType": 1,
                "param1": 3,
                "param2": -1,
                "next": -1,
                "param3": 42
            },
            "173": {
                "type": "type1",
                "next": -1,
                "param3": 81,
                "param4": 17
            },
            "174": {
                "type": "switch",
                "subType": 6,
                "param2": 304,
                "param3": 3,
                "param4": 2,
                "param5": 43
            },
            "175": {
                "type": "switch",
                "subType": 6,
                "param2": 140,
                "param3": 3,
                "param4": 2,
                "param5": 45
            },
            "176": {
                "type": "type3",
                "subType": 0,
                "param1": 0,
                "param2": 376,
                "next": 131,
                "param3": 0
            },
            "177": {
                "type": "switch",
                "subType": 6,
                "param2": 576,
                "param3": 3,
                "param4": 2,
                "param5": 47
            },
            "178": {
                "type": "switch",
                "subType": 6,
                "param2": 361,
                "param3": 3,
                "param4": 2,
                "param5": 49
            },
            "179": {
                "type": "type3",
                "subType": 0,
                "param1": 0,
                "param2": 361,
                "next": 192,
                "param3": 0
            },
            "180": {
                "type": "start",
                "next": 204
            },
            "181": {
                "type": "type3",
                "subType": 1,
                "param1": 25,
                "param2": 0,
                "next": 104,
                "param3": 40
            },
            "182": {
                "type": "type3",
                "subType": 0,
                "param1": 0,
                "param2": 653,
                "next": 186,
                "param3": 1
            },
            "183": {
                "type": "start",
                "next": 184
            },
            "184": {
                "type": "type1",
                "next": -1,
                "param3": 81,
                "param4": 45
            },
            "185": {
                "type": "type3",
                "subType": 0,
                "param1": 0,
                "param2": 581,
                "next": 168,
                "param3": 1
            },
            "186": {
                "type": "type3",
                "subType": 0,
                "param1": 0,
                "param2": 632,
                "next": 194,
                "param3": 1
            },
            "187": {
                "type": "type1",
                "next": -1,
                "param3": 81,
                "param4": 51
            },
            "188": {
                "type": "type1",
                "next": -1,
                "param3": 81,
                "param4": 50
            },
            "189": {
                "type": "type1",
                "next": 190,
                "param3": 81,
                "param4": 49
            },
            "190": {
                "type": "switch",
                "subType": 6,
                "param2": 0,
                "param3": 0,
                "param4": 2,
                "param5": 51
            },
            "191": {
                "type": "type3",
                "subType": 0,
                "param1": 0,
                "param2": 1001,
                "next": 23,
                "param3": 24
            },
            "192": {
                "type": "switch",
                "subType": 6,
                "param2": 296,
                "param3": 3,
                "param4": 2,
                "param5": 53
            },
            "193": {
                "type": "type3",
                "subType": 0,
                "param1": 0,
                "param2": 688,
                "next": 213,
                "param3": 0
            },
            "194": {
                "type": "type3",
                "subType": 0,
                "param1": 0,
                "param2": 679,
                "next": 215,
                "param3": 0
            },
            "195": {
                "type": "switch",
                "subType": 6,
                "param2": 725,
                "param3": 3,
                "param4": 2,
                "param5": 55
            },
            "196": {
                "type": "switch",
                "subType": 6,
                "param2": 725,
                "param3": 3,
                "param4": 2,
                "param5": 57
            },
            "197": {
                "type": "switch",
                "subType": 6,
                "param2": 725,
                "param3": 3,
                "param4": 2,
                "param5": 59
            },
            "198": {
                "type": "switch",
                "subType": 6,
                "param2": 725,
                "param3": 3,
                "param4": 2,
                "param5": 61
            },
            "199": {
                "type": "type3",
                "subType": 4,
                "param1": 0,
                "param2": 26,
                "next": 1,
                "param3": 13
            },
            "200": {
                "type": "type3",
                "subType": 4,
                "param1": 256,
                "param2": 2,
                "next": 122,
                "param3": 13
            },
            "201": {
                "type": "type3",
                "subType": 0,
                "param1": 0,
                "param2": 1004,
                "next": 102,
                "param3": 24
            },
            "202": {
                "type": "type3",
                "subType": 0,
                "param1": 0,
                "param2": 7,
                "next": 203,
                "param3": 24
            },
            "203": {
                "type": "type3",
                "subType": 0,
                "param1": 0,
                "param2": 30,
                "next": 137,
                "param3": 6
            },
            "204": {
                "type": "type3",
                "subType": 1,
                "param1": 30,
                "param2": 0,
                "next": 189,
                "param3": 39
            },
            "205": {
                "type": "type3",
                "subType": 1,
                "param1": 0,
                "param2": 100,
                "next": 206,
                "param3": 16
            },
            "206": {
                "type": "type3",
                "subType": 0,
                "param1": 0,
                "param2": 5,
                "next": 69,
                "param3": 6
            },
            "207": {
                "type": "type3",
                "subType": 1,
                "param1": 0,
                "param2": 0,
                "next": 58,
                "param3": 33
            },
            "208": {
                "type": "type3",
                "subType": 0,
                "param1": 0,
                "param2": 737,
                "next": 127,
                "param3": 0
            },
            "209": {
                "type": "type3",
                "subType": 0,
                "param1": 0,
                "param2": 737,
                "next": 125,
                "param3": 1
            },
            "210": {
                "type": "type3",
                "subType": 0,
                "param1": 0,
                "param2": 301,
                "next": 211,
                "param3": 1
            },
            "211": {
                "type": "type3",
                "subType": 1,
                "param1": 66,
                "param2": 0,
                "next": 198,
                "param3": 3
            },
            "212": {
                "type": "switch",
                "subType": 6,
                "param2": 725,
                "param3": 3,
                "param4": 2,
                "param5": 63
            },
            "213": {
                "type": "switch",
                "subType": 6,
                "param2": 549,
                "param3": 3,
                "param4": 2,
                "param5": 65
            },
            "214": {
                "type": "type3",
                "subType": 0,
                "param1": 0,
                "param2": 549,
                "next": 233,
                "param3": 1
            },
            "215": {
                "type": "switch",
                "subType": 6,
                "param2": 548,
                "param3": 3,
                "param4": 2,
                "param5": 67
            },
            "216": {
                "type": "type3",
                "subType": 0,
                "param1": 0,
                "param2": 549,
                "next": 225,
                "param3": 0
            },
            "217": {
                "type": "switch",
                "subType": 6,
                "param2": 551,
                "param3": 3,
                "param4": 2,
                "param5": 69
            },
            "218": {
                "type": "type3",
                "subType": 0,
                "param1": 0,
                "param2": 393,
                "next": 161,
                "param3": 0
            },
            "219": {
                "type": "switch",
                "subType": 6,
                "param2": 15,
                "param3": 3,
                "param4": 2,
                "param5": 71
            },
            "220": {
                "type": "switch",
                "subType": 6,
                "param2": 11,
                "param3": 3,
                "param4": 2,
                "param5": 73
            },
            "221": {
                "type": "type3",
                "subType": 0,
                "param1": 0,
                "param2": 112,
                "next": 40,
                "param3": 24
            },
            "222": {
                "type": "switch",
                "subType": 6,
                "param2": 575,
                "param3": 3,
                "param4": 2,
                "param5": 75
            },
            "223": {
                "type": "start",
                "next": 224
            },
            "224": {
                "type": "type1",
                "next": -1,
                "param3": 81,
                "param4": 46
            },
            "225": {
                "type": "switch",
                "subType": 6,
                "param2": 389,
                "param3": 3,
                "param4": 2,
                "param5": 77
            },
            "226": {
                "type": "type3",
                "subType": 0,
                "param1": 0,
                "param2": 390,
                "next": 227,
                "param3": 0
            },
            "227": {
                "type": "switch",
                "subType": 6,
                "param2": 392,
                "param3": 3,
                "param4": 2,
                "param5": 79
            },
            "228": {
                "type": "type3",
                "subType": 0,
                "param1": 0,
                "param2": 393,
                "next": 231,
                "param3": 0
            },
            "229": {
                "type": "switch",
                "subType": 6,
                "param2": 15,
                "param3": 3,
                "param4": 2,
                "param5": 81
            },
            "230": {
                "type": "switch",
                "subType": 6,
                "param2": 11,
                "param3": 3,
                "param4": 2,
                "param5": 83
            },
            "231": {
                "type": "switch",
                "subType": 6,
                "param2": 360,
                "param3": 3,
                "param4": 2,
                "param5": 85
            },
            "232": {
                "type": "type3",
                "subType": 0,
                "param1": 0,
                "param2": 1200,
                "next": -1,
                "param3": 0
            },
            "233": {
                "type": "switch",
                "subType": 6,
                "param2": 360,
                "param3": 3,
                "param4": 2,
                "param5": 87
            },
            "234": {
                "type": "type3",
                "subType": 0,
                "param1": 0,
                "param2": 1200,
                "next": 238,
                "param3": 0
            },
            "235": {
                "type": "switch",
                "subType": 6,
                "param2": 1110,
                "param3": 3,
                "param4": 2,
                "param5": 89
            },
            "236": {
                "type": "type3",
                "subType": 0,
                "param1": 0,
                "param2": 1110,
                "next": 237,
                "param3": 0
            },
            "237": {
                "type": "type3",
                "subType": 0,
                "param1": 0,
                "param2": 832,
                "next": -1,
                "param3": 0
            },
            "238": {
                "type": "type3",
                "subType": 1,
                "param1": 53,
                "param2": 0,
                "next": -1,
                "param3": 29
            }
        },
        "branch_points": [
            9,
            7,
            173,
            8,
            37,
            38,
            39,
            74,
            10,
            126,
            212,
            128,
            174,
            129,
            156,
            197,
            159,
            159,
            133,
            159,
            134,
            149,
            154,
            151,
            152,
            153,
            195,
            155,
            196,
            220,
            158,
            219,
            161,
            160,
            166,
            163,
            165,
            185,
            168,
            167,
            182,
            169,
            177,
            175,
            131,
            176,
            131,
            192,
            222,
            192,
            179,
            187,
            188,
            193,
            213,
            174,
            174,
            198,
            198,
            159,
            132,
            156,
            130,
            198,
            210,
            214,
            233,
            217,
            225,
            225,
            216,
            218,
            161,
            157,
            158,
            178,
            192,
            230,
            227,
            229,
            231,
            228,
            231,
            226,
            227,
            232,
            -1,
            234,
            238,
            -1,
            236
        ]
    },
    "FEN1": [
        [
            {
                "name": "102_15",
                "value": 183
            }
        ],
        [
            {
                "name": "102_16",
                "value": 223
            }
        ],
        [],
        [],
        [
            {
                "name": "102_01",
                "value": 0
            }
        ],
        [
            {
                "name": "102_02",
                "value": 2
            }
        ],
        [
            {
                "name": "102_03",
                "value": 4
            }
        ],
        [
            {
                "name": "102_04",
                "value": 6
            }
        ],
        [
            {
                "name": "102_05",
                "value": 11
            }
        ],
        [
            {
                "name": "102_06",
                "value": 22
            }
        ],
        [
            {
                "name": "102_07",
                "value": 71
            }
        ],
        [
            {
                "name": "102_08",
                "value": 82
            }
        ],
        [
            {
                "name": "102_09",
                "value": 88
            }
        ],
        [],
        [
            {
                "name": "102_10",
                "value": 112
            }
        ],
        [
            {
                "name": "102_11",
                "value": 121
            }
        ],
        [
            {
                "name": "102_12",
                "value": 123
            }
        ],
        [
            {
                "name": "102_13",
                "value": 124
            }
        ],
        [
            {
                "name": "102_14",
                "value": 180
            }
        ]
    ]
}