{
    "LYSE": [
        {
            "story_flag": 1098,
            "night": 0,
            "layer": 2
        },
        {
            "story_flag": -1,
            "night": 0,
            "layer": 1
        }
    ],
    "STIF": {
        "wtf1": 1.0,
        "wtf2": 160000.0,
        "wtf3": 10000.0,
        "byte1": 0,
        "flagindex": 20,
        "byte3": 1,
        "byte4": 0,
        "unk1": "FF 01",
        "map_name_id": 17,
        "unk2": "FF"
    },
    "RMPL": {
        "0": []
    },
    "LAY ": {
        "l0": {
            "OBJN": [
                "MapArea",
                "TlpTag",
                "lock",
                "TstShtr"
            ],
            "ARCN": [
                "ShutterFenced04"
            ],
            "DOOR": [
                {
                    "params1": "00 0C FC 42",
                    "params2": "FF 7F FF FF",
                    "posx": 1624.965576171875,
                    "posy": 0.0,
                    "posz": 899.0379638671875,
                    "anglex": 17727,
                    "angley": 0,
                    "anglez": 0,
                    "id": "FF FF",
                    "name": "TstShtr",
                    "extra_info": {
                        "side1scenefid": 63,
                        "side2scenefid": 69,
                        "side1scenef": "scene flag: 0x6 80",
                        "side2scenef": "scene flag: 0x9 20"
                    }
                }
            ],
            "STAG": [
                {
                    "params1": "FF FF FF 01",
                    "params2": "FF FF FF FF",
                    "posx": 0.0,
                    "posy": -2200.0,
                    "posz": 0.0,
                    "sizex": 10000.0,
                    "sizey": 5000.0,
                    "sizez": 10000.0,
                    "anglex": 0,
                    "angley": 0,
                    "anglez": 0,
                    "id": "FC 00",
                    "name": "MapArea"
                },
                {
                    "params1": "FF FF FF 00",
                    "params2": "FF FF FF FF",
                    "posx": 0.0,
                    "posy": -2200.0,
                    "posz": 0.0,
                    "sizex": 28000.0,
                    "sizey": 5000.0,
                    "sizez": 28000.0,
                    "anglex": 0,
                    "angley": 0,
                    "anglez": 0,
                    "id": "FC 01",
                    "name": "MapArea"
                },
                {
                    "params1": "B2 FF 11 FF",
                    "params2": "FF FF FF FF",
                    "posx": -3613.19384765625,
                    "posy": 1329.8802490234375,
                    "posz": -1808.615478515625,
                    "sizex": 100.0,
                    "sizey": 100.0,
                    "sizez": 100.0,
                    "anglex": 0,
                    "angley": 0,
                    "anglez": 0,
                    "id": "FC 02",
                    "name": "TlpTag",
                    "extra_info": {
                        "scenefid": 178,
                        "nameidx": 17,
                        "name": "Sky Keep",
                        "scenef": "temp flag: 0x7 04"
                    }
                }
            ]
        },
        "l1": {
            "OBJN": [
                "TstShtr"
            ],
            "ARCN": [
                "ShutterFenced04"
            ],
            "DOOR": [
                {
                    "params1": "00 0C FC 40",
                    "params2": "FF 7F FF FF",
                    "posx": -2090.0,
                    "posy": 0.0,
                    "posz": -100.0,
                    "anglex": 17867,
                    "angley": 32768,
                    "anglez": 0,
                    "id": "FF FF",
                    "name": "TstShtr",
                    "extra_info": {
                        "side1scenefid": 203,
                        "side2scenefid": 69,
                        "side1scenef": "loadzone temp flag: 0x0 08",
                        "side2scenef": "scene flag: 0x9 20"
                    }
                },
                {
                    "params1": "00 0D FC 40",
                    "params2": "FF 7F FF FF",
                    "posx": -355.6578369140625,
                    "posy": 0.0,
                    "posz": 1681.3878173828125,
                    "anglex": 65484,
                    "angley": 49152,
                    "anglez": 0,
                    "id": "FF FF",
                    "name": "TstShtr",
                    "extra_info": {
                        "side1scenefid": 204,
                        "side2scenefid": 255,
                        "side1scenef": "loadzone temp flag: 0x0 10",
                        "side2scenef": "no flag"
                    }
                },
                {
                    "params1": "00 0C FC 40",
                    "params2": "FF 7F FF FF",
                    "posx": 690.521240234375,
                    "posy": 0.0,
                    "posz": -2412.752197265625,
                    "anglex": 17866,
                    "angley": 16384,
                    "anglez": 0,
                    "id": "FF FF",
                    "name": "TstShtr",
                    "extra_info": {
                        "side1scenefid": 202,
                        "side2scenefid": 69,
                        "side1scenef": "loadzone temp flag: 0x0 04",
                        "side2scenef": "scene flag: 0x9 20"
                    }
                }
            ]
        },
        "l2": {
            "OBJN": [
                "TstShtr"
            ],
            "ARCN": [
                "ShutterFenced04"
            ],
            "DOOR": [
                {
                    "params1": "00 0C FC 40",
                    "params2": "FF 7F FF FF",
                    "posx": -2090.0,
                    "posy": 0.0,
                    "posz": -100.0,
                    "anglex": 17919,
                    "angley": 32768,
                    "anglez": 0,
                    "id": "FF FF",
                    "name": "TstShtr",
                    "extra_info": {
                        "side1scenefid": 255,
                        "side2scenefid": 69,
                        "side1scenef": "no flag",
                        "side2scenef": "scene flag: 0x9 20"
                    }
                },
                {
                    "params1": "00 0C FC 40",
                    "params2": "FF 7F FF FF",
                    "posx": -355.6578369140625,
                    "posy": 0.0,
                    "posz": 1681.3878173828125,
                    "anglex": 65535,
                    "angley": 49152,
                    "anglez": 0,
                    "id": "FF FF",
                    "name": "TstShtr",
                    "extra_info": {
                        "side1scenefid": 255,
                        "side2scenefid": 255,
                        "side1scenef": "no flag",
                        "side2scenef": "no flag"
                    }
                },
                {
                    "params1": "00 0C FC 40",
                    "params2": "FF 7F FF FF",
                    "posx": 690.521240234375,
                    "posy": 0.0,
                    "posz": -2412.752197265625,
                    "anglex": 17919,
                    "angley": 16384,
                    "anglez": 0,
                    "id": "FF FF",
                    "name": "TstShtr",
                    "extra_info": {
                        "side1scenefid": 255,
                        "side2scenefid": 69,
                        "side1scenef": "no flag",
                        "side2scenef": "scene flag: 0x9 20"
                    }
                }
            ]
        },
        "l3": {},
        "l4": {},
        "l5": {},
        "l6": {},
        "l7": {},
        "l8": {},
        "l9": {},
        "l10": {},
        "l11": {},
        "l12": {},
        "l13": {},
        "l14": {},
        "l15": {},
        "l16": {},
        "l17": {},
        "l18": {},
        "l19": {},
        "l20": {},
        "l21": {},
        "l22": {},
        "l23": {},
        "l24": {},
        "l25": {},
        "l26": {},
        "l27": {},
        "l28": {}
    },
    "rooms": {
        "r00": {
            "SCEN": [
                {
                    "name": "F000",
                    "room": 0,
                    "layer": 19,
                    "entrance": 54,
                    "byte4": 2,
                    "byte5": 0,
                    "flag6": 0,
                    "zero": 0,
                    "flag8": 0
                },
                {
                    "name": "F000",
                    "room": 0,
                    "layer": 0,
                    "entrance": 53,
                    "byte4": 2,
                    "byte5": 0,
                    "flag6": 0,
                    "zero": 0,
                    "flag8": 0
                },
                {
                    "name": "D003_8",
                    "room": 0,
                    "layer": 3,
                    "entrance": 0,
                    "byte4": 2,
                    "byte5": 1,
                    "flag6": 0,
                    "zero": 0,
                    "flag8": 0
                },
                {
                    "name": "F000",
                    "room": 0,
                    "layer": 0,
                    "entrance": 53,
                    "byte4": 2,
                    "byte5": 2,
                    "flag6": 0,
                    "zero": 0,
                    "flag8": 0
                }
            ],
            "CAM ": [
                {
                    "unk1": "FF FF FF FF",
                    "posx": -3380.47900390625,
                    "posy": 1110.7784423828125,
                    "posz": 4489.5830078125,
                    "angle": 45.0,
                    "unk2": "00 00 80 00 00 00 00 00",
                    "name": "D3R00Hashi"
                },
                {
                    "unk1": "FF FF FF FF",
                    "posx": -2747.555419921875,
                    "posy": 1089.8203125,
                    "posz": 4499.62939453125,
                    "angle": 45.0,
                    "unk2": "00 00 80 00 00 00 00 01",
                    "name": "D3R00Arrow"
                }
            ],
            "PATH": [
                "FF 00 00 00 00 02 FF FF FF FF 00 FF",
                "FF 01 00 02 00 02 FF FF FF FF 00 FF"
            ],
            "PNT ": [
                {
                    "posx": 1625.0,
                    "posy": 10.0,
                    "posz": -2396.527099609375,
                    "unk": "FF FF FF FF"
                },
                {
                    "posx": 1625.0,
                    "posy": 10.0,
                    "posz": -1554.0633544921875,
                    "unk": "FF FF FF FF"
                },
                {
                    "posx": 1625.0,
                    "posy": 10.0,
                    "posz": -1066.8917236328125,
                    "unk": "FF FF FF FF"
                },
                {
                    "posx": 1625.0,
                    "posy": 10.0,
                    "posz": -181.44769287109375,
                    "unk": "FF FF FF FF"
                }
            ],
            "AREA": [
                {
                    "posx": 1092.25537109375,
                    "posy": -20.0,
                    "posz": 1053.006103515625,
                    "sizex": 900.0,
                    "sizey": 1000.0,
                    "sizez": 900.0,
                    "angley": 0,
                    "area_link": -1,
                    "unk3": 1,
                    "dummy": "FF FF FF",
                    "index": 0
                },
                {
                    "posx": 276.9949035644531,
                    "posy": -103.01380157470703,
                    "posz": 1670.153564453125,
                    "sizex": 500.0,
                    "sizey": 1000.0,
                    "sizez": 1000.0,
                    "angley": 0,
                    "area_link": -1,
                    "unk3": 0,
                    "dummy": "FF FF FF",
                    "index": 1
                }
            ],
            "EVNT": [
                {
                    "unk1": "00 00",
                    "story_flag1": -1,
                    "story_flag2": -1,
                    "unk2": "64 00 FF",
                    "exit_id": -1,
                    "unk3": "00 00 00",
                    "skipevent": -1,
                    "unk4": "FF",
                    "sceneflag1": 255,
                    "sceneflag2": 255,
                    "skipflag": 255,
                    "dummy1": -1,
                    "item": -1,
                    "dummy2": -1,
                    "name": "-"
                },
                {
                    "unk1": "00 00",
                    "story_flag1": 1098,
                    "story_flag2": -1,
                    "unk2": "64 01 FF",
                    "exit_id": -1,
                    "unk3": "00 00 00",
                    "skipevent": -1,
                    "unk4": "FF",
                    "sceneflag1": 255,
                    "sceneflag2": 255,
                    "skipflag": 255,
                    "dummy1": -1,
                    "item": -1,
                    "dummy2": -1,
                    "name": "WaitD003"
                }
            ],
            "PLY ": [
                {
                    "storyflag": 2047,
                    "play_cutscene": -1,
                    "byte4": 4,
                    "posx": 3147.214599609375,
                    "posy": 0.0,
                    "posz": 2.648577928543091,
                    "anglex": 0,
                    "angley": 49152,
                    "anglez": 0,
                    "entrance_id": 1
                },
                {
                    "storyflag": 2047,
                    "play_cutscene": -1,
                    "byte4": 4,
                    "posx": -0.09091699868440628,
                    "posy": 0.0,
                    "posz": 3149.374267578125,
                    "anglex": 0,
                    "angley": 32768,
                    "anglez": 0,
                    "entrance_id": 2
                },
                {
                    "storyflag": 2047,
                    "play_cutscene": -1,
                    "byte4": 4,
                    "posx": -2894.65087890625,
                    "posy": 0.0,
                    "posz": 128.9694366455078,
                    "anglex": 0,
                    "angley": 16384,
                    "anglez": 0,
                    "entrance_id": 3
                },
                {
                    "storyflag": 2047,
                    "play_cutscene": -1,
                    "byte4": 4,
                    "posx": 2.764389991760254,
                    "posy": 0.0,
                    "posz": 3168.394775390625,
                    "anglex": 0,
                    "angley": 32768,
                    "anglez": 0,
                    "entrance_id": 4
                },
                {
                    "storyflag": 2047,
                    "play_cutscene": -1,
                    "byte4": 20,
                    "posx": 250.0,
                    "posy": 28.520000457763672,
                    "posz": 1675.0,
                    "anglex": 0,
                    "angley": 16384,
                    "anglez": 0,
                    "entrance_id": 10
                },
                {
                    "storyflag": 2047,
                    "play_cutscene": -1,
                    "byte4": -1,
                    "posx": 1616.0863037109375,
                    "posy": 0.0,
                    "posz": 569.6045532226562,
                    "anglex": 0,
                    "angley": 32768,
                    "anglez": 0,
                    "entrance_id": 5
                }
            ],
            "LAY ": {
                "l0": {
                    "OBJN": [
                        "SwdStb",
                        "TgD3Chg",
                        "V_Clip",
                        "CtrlPnl",
                        "NpcTke",
                        "Heartf",
                        "FShutte",
                        "ShtCS",
                        "EvntTag",
                        "DieTag",
                        "BtlTg",
                        "CamTag",
                        "Item",
                        "TgSndMg",
                        "SwAreaT",
                        "PlRsTag",
                        "skull",
                        "SwWall",
                        "D3Dummy",
                        "Bombf",
                        "TgSndAr"
                    ],
                    "ARCN": [
                        "PLSwordStick",
                        "PLObjHang",
                        "ShutterFenced04",
                        "PutTriForceSingle",
                        "D3MapDummy",
                        "ShutterFenceOnly00",
                        "GetTriForceSingle",
                        "ControlPanel",
                        "Skull"
                    ],
                    "OBJS": [
                        {
                            "params1": "FF F8 00 40",
                            "params2": "FF 7F FF FF",
                            "posx": 3150.0,
                            "posy": 0.0,
                            "posz": 0.0,
                            "anglex": 65535,
                            "angley": 49152,
                            "anglez": 0,
                            "id": "FC 00",
                            "name": "ShtCS",
                            "extra_info": {
                                "scenefid": 0,
                                "scenef": "scene flag: 0x1 01"
                            }
                        },
                        {
                            "params1": "FF F8 04 40",
                            "params2": "FF 7F FF FF",
                            "posx": 0.0,
                            "posy": 0.0,
                            "posz": 3150.0,
                            "anglex": 65535,
                            "angley": 32768,
                            "anglez": 0,
                            "id": "FC 01",
                            "name": "ShtCS",
                            "extra_info": {
                                "scenefid": 1,
                                "scenef": "scene flag: 0x1 02"
                            }
                        }
                    ],
                    "OBJ ": [
                        {
                            "params1": "FF FF FF 14",
                            "params2": "FF FF FF FF",
                            "posx": 855.666748046875,
                            "posy": 0.0,
                            "posz": 1679.1390380859375,
                            "anglex": 0,
                            "angley": 49152,
                            "anglez": 0,
                            "id": "FC 02",
                            "name": "FShutte",
                            "extra_info": {
                                "scenefid": 20,
                                "scenef": "scene flag: 0x3 10"
                            }
                        },
                        {
                            "params1": "FF FF FF FF",
                            "params2": "FF FF FF FF",
                            "posx": -3781.02587890625,
                            "posy": 0.0,
                            "posz": 22.014707565307617,
                            "anglex": 0,
                            "angley": 0,
                            "anglez": 0,
                            "id": "FC 03",
                            "name": "D3Dummy"
                        },
                        {
                            "params1": "FF 0D 02 60",
                            "params2": "FF FF FF FF",
                            "posx": 255.34771728515625,
                            "posy": 5000.0,
                            "posz": 1681.5970458984375,
                            "anglex": 0,
                            "angley": 16384,
                            "anglez": 0,
                            "id": "FC 04",
                            "name": "Item",
                            "extra_info": {
                                "scenefid": 64,
                                "itemid": 96,
                                "item": "Triforce of Power",
                                "scenef": "scene flag: 0x9 01"
                            }
                        },
                        {
                            "params1": "FF FF 14 FF",
                            "params2": "FF FF FF FF",
                            "posx": 750.0,
                            "posy": 300.0,
                            "posz": 1404.644287109375,
                            "anglex": 0,
                            "angley": 49152,
                            "anglez": 0,
                            "id": "FC 05",
                            "name": "SwWall",
                            "extra_info": {
                                "scenefid": 20,
                                "scenef": "scene flag: 0x3 10"
                            }
                        },
                        {
                            "params1": "FF F9 90 FF",
                            "params2": "FF FF FF FF",
                            "posx": -3286.08837890625,
                            "posy": 1003.9608764648438,
                            "posz": -1669.01318359375,
                            "anglex": 0,
                            "angley": 0,
                            "anglez": 0,
                            "id": "FC 06",
                            "name": "Heartf",
                            "extra_info": {
                                "scenefid": 153,
                                "scenef": "temp flag: 0x2 02"
                            }
                        },
                        {
                            "params1": "FF F9 A0 FF",
                            "params2": "FF FF FF FF",
                            "posx": -3235.64404296875,
                            "posy": 1011.4341430664062,
                            "posz": -1474.4415283203125,
                            "anglex": 0,
                            "angley": 0,
                            "anglez": 0,
                            "id": "FC 07",
                            "name": "Heartf",
                            "extra_info": {
                                "scenefid": 154,
                                "scenef": "temp flag: 0x2 04"
                            }
                        },
                        {
                            "params1": "FF F9 B0 FF",
                            "params2": "FF FF FF FF",
                            "posx": -3260.056396484375,
                            "posy": 1001.8372802734375,
                            "posz": -1869.172119140625,
                            "anglex": 0,
                            "angley": 0,
                            "anglez": 0,
                            "id": "FC 08",
                            "name": "Heartf",
                            "extra_info": {
                                "scenefid": 155,
                                "scenef": "temp flag: 0x2 08"
                            }
                        },
                        {
                            "params1": "FF FF FF FF",
                            "params2": "04 FF FF FF",
                            "posx": -2410.515625,
                            "posy": 4.373863220214844,
                            "posz": 2107.118408203125,
                            "anglex": 0,
                            "angley": 32768,
                            "anglez": 0,
                            "id": "FC 09",
                            "name": "skull"
                        },
                        {
                            "params1": "FF FF FF FF",
                            "params2": "04 FF FF FF",
                            "posx": -1617.816162109375,
                            "posy": 4.694663047790527,
                            "posz": 2337.7216796875,
                            "anglex": 0,
                            "angley": 32768,
                            "anglez": 0,
                            "id": "FC 0A",
                            "name": "skull"
                        },
                        {
                            "params1": "FF FF FF FF",
                            "params2": "04 FF FF FF",
                            "posx": -2480.960205078125,
                            "posy": -1.2402160167694092,
                            "posz": -1909.3306884765625,
                            "anglex": 0,
                            "angley": 16384,
                            "anglez": 0,
                            "id": "FC 0B",
                            "name": "skull"
                        },
                        {
                            "params1": "FF FF FF FF",
                            "params2": "04 FF FF FF",
                            "posx": -1320.73681640625,
                            "posy": -4.290224075317383,
                            "posz": -511.29742431640625,
                            "anglex": 0,
                            "angley": 32768,
                            "anglez": 0,
                            "id": "FC 0C",
                            "name": "skull"
                        },
                        {
                            "params1": "FF FF FF F0",
                            "params2": "FF FF FF FF",
                            "posx": 92.88402557373047,
                            "posy": 396.8500061035156,
                            "posz": -2036.537109375,
                            "anglex": 0,
                            "angley": 0,
                            "anglez": 0,
                            "id": "FC 0D",
                            "name": "Bombf"
                        },
                        {
                            "params1": "FF FF FF FF",
                            "params2": "04 FF FF FF",
                            "posx": -1189.9967041015625,
                            "posy": 4.760000228881836,
                            "posz": 1906.533447265625,
                            "anglex": 0,
                            "angley": 40960,
                            "anglez": 0,
                            "id": "FC 0E",
                            "name": "skull"
                        },
                        {
                            "params1": "FF FF FF 02",
                            "params2": "FF 1F FF FF",
                            "posx": 3622.5185546875,
                            "posy": 565.8682861328125,
                            "posz": 1966.5101318359375,
                            "anglex": 11263,
                            "angley": 65280,
                            "anglez": 12505,
                            "id": "FC 0F",
                            "name": "NpcTke",
                            "extra_info": {
                                "trigstoryfid": 2047,
                                "untrigstoryfid": 2047,
                                "talk_behaviour": 12505,
                                "triggerarea": 0,
                                "trigscenefid": 255,
                                "untrigscenefid": 43,
                                "trigstoryf": "-",
                                "untrigstoryf": "-",
                                "trigscenef": "no flag",
                                "untrigscenef": "scene flag: 0x4 08"
                            }
                        },
                        {
                            "params1": "FF FC 0B 60",
                            "params2": "FF FF FF FF",
                            "posx": 250.0,
                            "posy": 28.520000457763672,
                            "posz": 1675.0,
                            "anglex": 0,
                            "angley": 49152,
                            "anglez": 0,
                            "id": "FC 10",
                            "name": "SwdStb",
                            "extra_info": {
                                "scenefid": 96,
                                "scenef": "scene flag: 0xD 01"
                            }
                        },
                        {
                            "params1": "FF FF FF 02",
                            "params2": "FF 1F FF FF",
                            "posx": -1792.759521484375,
                            "posy": 5945.82861328125,
                            "posz": 4468.234375,
                            "anglex": 6399,
                            "angley": 65281,
                            "anglez": 12511,
                            "id": "FC 11",
                            "name": "NpcTke",
                            "extra_info": {
                                "trigstoryfid": 2047,
                                "untrigstoryfid": 2047,
                                "talk_behaviour": 12511,
                                "triggerarea": 1,
                                "trigscenefid": 255,
                                "untrigscenefid": 24,
                                "trigstoryf": "-",
                                "untrigstoryf": "-",
                                "trigscenef": "no flag",
                                "untrigscenef": "scene flag: 0x2 01"
                            }
                        },
                        {
                            "params1": "FD FF 00 00",
                            "params2": "FF FF FF FF",
                            "posx": -3965.951171875,
                            "posy": 2020.8333740234375,
                            "posz": -3725.590576171875,
                            "anglex": 0,
                            "angley": 0,
                            "anglez": 0,
                            "id": "FC 12",
                            "name": "CtrlPnl"
                        }
                    ],
                    "STAG": [
                        {
                            "params1": "FF CF FF 05",
                            "params2": "FF DF FF FF",
                            "posx": 1929.892822265625,
                            "posy": -3000.0,
                            "posz": -1968.3052978515625,
                            "sizex": 2500.0,
                            "sizey": 4000.0,
                            "sizez": 3000.0,
                            "anglex": 0,
                            "angley": 0,
                            "anglez": 65535,
                            "id": "FC 13",
                            "name": "PlRsTag",
                            "extra_info": {
                                "trigscenefid": 255,
                                "untrigscenefid": 255,
                                "entranceid": 5,
                                "trigscenef": "no flag",
                                "untrigscenef": "no flag"
                            }
                        },
                        {
                            "params1": "FF CF FF 05",
                            "params2": "FF DF FF FF",
                            "posx": 1430.44140625,
                            "posy": -3000.0,
                            "posz": -134.25430297851562,
                            "sizex": 1500.0,
                            "sizey": 4000.0,
                            "sizez": 2000.0,
                            "anglex": 0,
                            "angley": 0,
                            "anglez": 65535,
                            "id": "FC 14",
                            "name": "PlRsTag",
                            "extra_info": {
                                "trigscenefid": 255,
                                "untrigscenefid": 255,
                                "entranceid": 5,
                                "trigscenef": "no flag",
                                "untrigscenef": "no flag"
                            }
                        },
                        {
                            "params1": "FF CC 76 01",
                            "params2": "FF FF FF FF",
                            "posx": -1866.6358642578125,
                            "posy": -308.93060302734375,
                            "posz": 1559.36474609375,
                            "sizex": 3500.0,
                            "sizey": 5000.0,
                            "sizez": 3500.0,
                            "anglex": 0,
                            "angley": 0,
                            "anglez": 0,
                            "id": "FC 15",
                            "name": "EvntTag",
                            "extra_info": {
                                "trigscenefid": 204,
                                "setscenefid": 118,
                                "event": 1,
                                "trigscenef": "loadzone temp flag: 0x0 10",
                                "setscenef": "scene flag: 0xF 40"
                            }
                        },
                        {
                            "params1": "FF FF F1 C2",
                            "params2": "FF FF FF FF",
                            "posx": 2685.021240234375,
                            "posy": -100.0,
                            "posz": 287.6673889160156,
                            "sizex": 1000.0,
                            "sizey": 600.0,
                            "sizez": 1500.0,
                            "anglex": 0,
                            "angley": 0,
                            "anglez": 0,
                            "id": "FC 16",
                            "name": "V_Clip"
                        },
                        {
                            "params1": "FF FF FF F1",
                            "params2": "FF FF FF FF",
                            "posx": 3500.0,
                            "posy": -80.0,
                            "posz": 0.0,
                            "sizex": 500.0,
                            "sizey": 500.0,
                            "sizez": 500.0,
                            "anglex": 0,
                            "angley": 0,
                            "anglez": 0,
                            "id": "FC 17",
                            "name": "TgD3Chg"
                        },
                        {
                            "params1": "FF FF FF F2",
                            "params2": "FF FF FF FF",
                            "posx": 0.0,
                            "posy": -80.0,
                            "posz": 3500.0,
                            "sizex": 500.0,
                            "sizey": 500.0,
                            "sizez": 500.0,
                            "anglex": 0,
                            "angley": 0,
                            "anglez": 0,
                            "id": "FC 18",
                            "name": "TgD3Chg"
                        },
                        {
                            "params1": "FF FF FF 00",
                            "params2": "FF DF FF FF",
                            "posx": 1448.0,
                            "posy": -1000.0,
                            "posz": -978.0,
                            "sizex": 1500.0,
                            "sizey": 2000.0,
                            "sizez": 4000.0,
                            "anglex": 0,
                            "angley": 0,
                            "anglez": 65535,
                            "id": "FC 19",
                            "name": "CamTag",
                            "extra_info": {
                                "trigscenefid": 255,
                                "untrigscenefid": 255,
                                "camidx": 0,
                                "trigscenef": "no flag",
                                "untrigscenef": "no flag"
                            }
                        },
                        {
                            "params1": "FF FF FF 01",
                            "params2": "FF DF FF FF",
                            "posx": -1307.0,
                            "posy": -1000.0,
                            "posz": -1604.0,
                            "sizex": 4000.0,
                            "sizey": 2500.0,
                            "sizez": 3000.0,
                            "anglex": 0,
                            "angley": 0,
                            "anglez": 65535,
                            "id": "FC 1A",
                            "name": "CamTag",
                            "extra_info": {
                                "trigscenefid": 255,
                                "untrigscenefid": 255,
                                "camidx": 1,
                                "trigscenef": "no flag",
                                "untrigscenef": "no flag"
                            }
                        },
                        {
                            "params1": "FF FF FF FF",
                            "params2": "FF 5F FF FF",
                            "posx": 3160.0,
                            "posy": -80.0,
                            "posz": 0.0,
                            "sizex": 500.0,
                            "sizey": 500.0,
                            "sizez": 500.0,
                            "anglex": 64181,
                            "angley": 0,
                            "anglez": 65535,
                            "id": "FC 1B",
                            "name": "SwAreaT",
                            "extra_info": {
                                "setstoryfid": 693,
                                "unsetstoryfid": 2047,
                                "setscenefid": 255,
                                "unsetscenefid": 255,
                                "setstoryf": "Going near first door in Sky keep",
                                "unsetstoryf": "-",
                                "setscenef": "no flag",
                                "unsetscenef": "no flag"
                            }
                        },
                        {
                            "params1": "FF FF F1 C1",
                            "params2": "FF FF FF FF",
                            "posx": -1328.5030517578125,
                            "posy": -100.0,
                            "posz": -1654.577392578125,
                            "sizex": 4000.0,
                            "sizey": 2000.0,
                            "sizez": 3000.0,
                            "anglex": 0,
                            "angley": 0,
                            "anglez": 0,
                            "id": "FC 1C",
                            "name": "V_Clip"
                        },
                        {
                            "params1": "FF FF F1 C2",
                            "params2": "FF FF FF FF",
                            "posx": -1328.5029296875,
                            "posy": -100.0,
                            "posz": -1654.5775146484375,
                            "sizex": 4000.0,
                            "sizey": 2000.0,
                            "sizez": 3000.0,
                            "anglex": 0,
                            "angley": 0,
                            "anglez": 0,
                            "id": "FC 1D",
                            "name": "V_Clip"
                        },
                        {
                            "params1": "FF FF FF D2",
                            "params2": "FF FF FF FF",
                            "posx": -1886.6416015625,
                            "posy": 600.0,
                            "posz": 1533.480712890625,
                            "sizex": 1500.0,
                            "sizey": 2000.0,
                            "sizez": 1500.0,
                            "anglex": 0,
                            "angley": 0,
                            "anglez": 0,
                            "id": "FC 1E",
                            "name": "BtlTg"
                        },
                        {
                            "params1": "FF FF FC C0",
                            "params2": "FF 7F FF FF",
                            "posx": -1851.5626220703125,
                            "posy": -5000.0,
                            "posz": 1503.3448486328125,
                            "sizex": 3000.0,
                            "sizey": 7000.0,
                            "sizez": 3200.0,
                            "anglex": 65533,
                            "angley": 0,
                            "anglez": 0,
                            "id": "FC 1F",
                            "name": "DieTag",
                            "extra_info": {
                                "setscenefid": 204,
                                "setscenef": "loadzone temp flag: 0x0 10"
                            }
                        },
                        {
                            "params1": "FF FF FC B0",
                            "params2": "FF 7F FF FF",
                            "posx": -1307.497802734375,
                            "posy": -5000.0,
                            "posz": -1604.0135498046875,
                            "sizex": 4000.0,
                            "sizey": 7000.0,
                            "sizez": 3000.0,
                            "anglex": 65533,
                            "angley": 0,
                            "anglez": 0,
                            "id": "FC 20",
                            "name": "DieTag",
                            "extra_info": {
                                "setscenefid": 203,
                                "setscenef": "loadzone temp flag: 0x0 08"
                            }
                        },
                        {
                            "params1": "FF FF FC A0",
                            "params2": "FF 7F FF FF",
                            "posx": 1448.9046630859375,
                            "posy": -5000.0,
                            "posz": -978.2730712890625,
                            "sizex": 1500.0,
                            "sizey": 7000.0,
                            "sizez": 4000.0,
                            "anglex": 65533,
                            "angley": 0,
                            "anglez": 0,
                            "id": "FC 21",
                            "name": "DieTag",
                            "extra_info": {
                                "setscenefid": 202,
                                "setscenef": "loadzone temp flag: 0x0 04"
                            }
                        },
                        {
                            "params1": "FF FF FF FF",
                            "params2": "FF 5F FF FF",
                            "posx": 0.0,
                            "posy": -1000.0,
                            "posz": 0.0,
                            "sizex": 6500.0,
                            "sizey": 6000.0,
                            "sizez": 6500.0,
                            "anglex": 64182,
                            "angley": 0,
                            "anglez": 65535,
                            "id": "FC 22",
                            "name": "SwAreaT",
                            "extra_info": {
                                "setstoryfid": 694,
                                "unsetstoryfid": 2047,
                                "setscenefid": 255,
                                "unsetscenefid": 255,
                                "setstoryf": "",
                                "unsetstoryf": "-",
                                "setscenef": "no flag",
                                "unsetscenef": "no flag"
                            }
                        },
                        {
                            "params1": "FF FF FF C2",
                            "params2": "FF FF FF FF",
                            "posx": 1327.36181640625,
                            "posy": -2700.0,
                            "posz": 219.30459594726562,
                            "sizex": 4000.0,
                            "sizey": 2000.0,
                            "sizez": 8000.0,
                            "anglex": 0,
                            "angley": 0,
                            "anglez": 0,
                            "id": "FC 23",
                            "name": "BtlTg"
                        },
                        {
                            "params1": "FF FF FF C2",
                            "params2": "FF FF FF FF",
                            "posx": -1868.2406005859375,
                            "posy": 1100.0,
                            "posz": 1432.0401611328125,
                            "sizex": 2500.0,
                            "sizey": 1000.0,
                            "sizez": 2500.0,
                            "anglex": 0,
                            "angley": 0,
                            "anglez": 0,
                            "id": "FC 24",
                            "name": "BtlTg"
                        }
                    ],
                    "SNDT": [
                        {
                            "params1": "0F FF FF 01",
                            "params2": "FF FF FF FF",
                            "posx": 1500.0,
                            "posy": -1482.61962890625,
                            "posz": -1100.0,
                            "sizex": 1800.0,
                            "sizey": 3000.0,
                            "sizez": 4000.0,
                            "anglex": 0,
                            "angley": 64080,
                            "anglez": 0,
                            "id": "FC 25",
                            "name": "TgSndAr"
                        },
                        {
                            "params1": "0F FF FF 02",
                            "params2": "FF FF FF FF",
                            "posx": -1350.0,
                            "posy": -47.51131057739258,
                            "posz": -1600.0,
                            "sizex": 3924.0,
                            "sizey": 1532.0,
                            "sizez": 2967.0,
                            "anglex": 0,
                            "angley": 64444,
                            "anglez": 0,
                            "id": "FC 26",
                            "name": "TgSndAr"
                        },
                        {
                            "params1": "0F FF FF 03",
                            "params2": "FF FF FF FF",
                            "posx": -1800.0,
                            "posy": -47.51131057739258,
                            "posz": 1400.0,
                            "sizex": 2900.0,
                            "sizey": 1580.0,
                            "sizez": 2900.0,
                            "anglex": 0,
                            "angley": 0,
                            "anglez": 0,
                            "id": "FC 27",
                            "name": "TgSndAr"
                        }
                    ]
                },
                "l1": {
                    "OBJN": [
                        "EBcZ",
                        "BcArrow",
                        "ESf",
                        "EBc",
                        "ESf4",
                        "EMr"
                    ],
                    "ARCN": [
                        "Sf4",
                        "GetSozaiO",
                        "Moriburin_Iron",
                        "Sf",
                        "Bocoburin_Z",
                        "GetSozaiK",
                        "GetSozaiL",
                        "MoriburinAnm"
                    ],
                    "OBJ ": [
                        {
                            "params1": "FF 01 01 00",
                            "params2": "14 DF FF FF",
                            "posx": 1630.0,
                            "posy": 0.0,
                            "posz": -1045.4013671875,
                            "anglex": 0,
                            "angley": 0,
                            "anglez": 65535,
                            "id": "08 28",
                            "name": "EMr",
                            "extra_info": {
                                "setscenefid": 255,
                                "setscenef": "no flag"
                            }
                        },
                        {
                            "params1": "FF 00 01 00",
                            "params2": "14 DF FF FF",
                            "posx": 1650.0,
                            "posy": 0.0,
                            "posz": -2396.527099609375,
                            "anglex": 0,
                            "angley": 0,
                            "anglez": 65535,
                            "id": "08 29",
                            "name": "EMr",
                            "extra_info": {
                                "setscenefid": 255,
                                "setscenef": "no flag"
                            }
                        },
                        {
                            "params1": "D9 FF 9F FD",
                            "params2": "25 5F FF FF",
                            "posx": -233.1350860595703,
                            "posy": 723.5400390625,
                            "posz": -1357.5887451171875,
                            "anglex": 65535,
                            "angley": 43691,
                            "anglez": 65535,
                            "id": "00 2A",
                            "name": "EBc",
                            "extra_info": {
                                "setscenefid": 255,
                                "setscenef": "no flag"
                            }
                        },
                        {
                            "params1": "D9 FF 9F FD",
                            "params2": "25 5F FF FF",
                            "posx": -2845.42626953125,
                            "posy": 389.7801208496094,
                            "posz": -1648.4859619140625,
                            "anglex": 65535,
                            "angley": 16384,
                            "anglez": 65535,
                            "id": "00 2B",
                            "name": "EBc",
                            "extra_info": {
                                "setscenefid": 255,
                                "setscenef": "no flag"
                            }
                        },
                        {
                            "params1": "D9 FF 9F FD",
                            "params2": "25 5F FF FF",
                            "posx": -799.4052734375,
                            "posy": 325.280029296875,
                            "posz": -977.6963500976562,
                            "anglex": 65535,
                            "angley": 32768,
                            "anglez": 65535,
                            "id": "00 2C",
                            "name": "EBc",
                            "extra_info": {
                                "setscenefid": 255,
                                "setscenef": "no flag"
                            }
                        },
                        {
                            "params1": "D9 FF 9F FD",
                            "params2": "25 5F FF FF",
                            "posx": -2798.60546875,
                            "posy": 967.7618408203125,
                            "posz": -1954.2247314453125,
                            "anglex": 65535,
                            "angley": 16384,
                            "anglez": 65535,
                            "id": "00 2D",
                            "name": "EBc",
                            "extra_info": {
                                "setscenefid": 255,
                                "setscenef": "no flag"
                            }
                        },
                        {
                            "params1": "D9 FF 9F FD",
                            "params2": "25 5F FF FF",
                            "posx": -1726.6429443359375,
                            "posy": 350.32000732421875,
                            "posz": -2305.0556640625,
                            "anglex": 65535,
                            "angley": 8192,
                            "anglez": 65535,
                            "id": "00 2E",
                            "name": "EBc",
                            "extra_info": {
                                "setscenefid": 255,
                                "setscenef": "no flag"
                            }
                        },
                        {
                            "params1": "FF FF FF FE",
                            "params2": "25 5F FF FF",
                            "posx": -2250.726318359375,
                            "posy": -1.2323700189590454,
                            "posz": -1108.49658203125,
                            "anglex": 65535,
                            "angley": 16384,
                            "anglez": 65535,
                            "id": "00 2F",
                            "name": "EBc",
                            "extra_info": {
                                "setscenefid": 255,
                                "setscenef": "no flag"
                            }
                        },
                        {
                            "params1": "FF FF FF FE",
                            "params2": "25 5F FF FF",
                            "posx": -1586.9718017578125,
                            "posy": -67.52513885498047,
                            "posz": -1289.5950927734375,
                            "anglex": 65535,
                            "angley": 16384,
                            "anglez": 65535,
                            "id": "00 30",
                            "name": "EBc",
                            "extra_info": {
                                "setscenefid": 255,
                                "setscenef": "no flag"
                            }
                        },
                        {
                            "params1": "FF FF FF FE",
                            "params2": "25 5F FF FF",
                            "posx": -922.7150268554688,
                            "posy": -51.2323112487793,
                            "posz": -1422.1268310546875,
                            "anglex": 65535,
                            "angley": 16384,
                            "anglez": 65535,
                            "id": "00 31",
                            "name": "EBc",
                            "extra_info": {
                                "setscenefid": 255,
                                "setscenef": "no flag"
                            }
                        },
                        {
                            "params1": "FF FF FF FE",
                            "params2": "25 5F FF FF",
                            "posx": -405.6606140136719,
                            "posy": -46.76580810546875,
                            "posz": -1625.4403076171875,
                            "anglex": 65535,
                            "angley": 16384,
                            "anglez": 65535,
                            "id": "00 32",
                            "name": "EBc",
                            "extra_info": {
                                "setscenefid": 255,
                                "setscenef": "no flag"
                            }
                        },
                        {
                            "params1": "FF FF FF FE",
                            "params2": "25 5F FF FF",
                            "posx": -2249.25927734375,
                            "posy": 0.029999999329447746,
                            "posz": -2081.08935546875,
                            "anglex": 65535,
                            "angley": 16384,
                            "anglez": 65535,
                            "id": "00 33",
                            "name": "EBc",
                            "extra_info": {
                                "setscenefid": 255,
                                "setscenef": "no flag"
                            }
                        },
                        {
                            "params1": "D9 FF 9F FD",
                            "params2": "25 5F FF FF",
                            "posx": -2794.05908203125,
                            "posy": 964.3275146484375,
                            "posz": -1379.6207275390625,
                            "anglex": 65535,
                            "angley": 16384,
                            "anglez": 65535,
                            "id": "00 34",
                            "name": "EBc",
                            "extra_info": {
                                "setscenefid": 255,
                                "setscenef": "no flag"
                            }
                        },
                        {
                            "params1": "FF AB 53 FD",
                            "params2": "25 FF FF FF",
                            "posx": -2505.39111328125,
                            "posy": 4.688408851623535,
                            "posz": 1783.7769775390625,
                            "anglex": 0,
                            "angley": 27306,
                            "anglez": 0,
                            "id": "04 35",
                            "name": "EBcZ"
                        },
                        {
                            "params1": "FF AB 53 FD",
                            "params2": "25 FF FF FF",
                            "posx": -2060.736083984375,
                            "posy": 4.402681827545166,
                            "posz": 2221.079345703125,
                            "anglex": 0,
                            "angley": 32768,
                            "anglez": 0,
                            "id": "04 36",
                            "name": "EBcZ"
                        },
                        {
                            "params1": "FF AB 53 FD",
                            "params2": "25 FF FF FF",
                            "posx": -1438.96728515625,
                            "posy": 4.760000228881836,
                            "posz": 2162.896484375,
                            "anglex": 0,
                            "angley": 40960,
                            "anglez": 0,
                            "id": "04 37",
                            "name": "EBcZ"
                        },
                        {
                            "params1": "FF AB 53 FD",
                            "params2": "25 FF FF FF",
                            "posx": -1045.146484375,
                            "posy": 4.760000228881836,
                            "posz": 1535.87841796875,
                            "anglex": 0,
                            "angley": 43691,
                            "anglez": 0,
                            "id": "04 38",
                            "name": "EBcZ"
                        },
                        {
                            "params1": "FF AB 53 FD",
                            "params2": "25 FF FF FF",
                            "posx": -1166.0428466796875,
                            "posy": 4.760000228881836,
                            "posz": 1762.5579833984375,
                            "anglex": 0,
                            "angley": 40960,
                            "anglez": 0,
                            "id": "04 39",
                            "name": "EBcZ"
                        },
                        {
                            "params1": "FF FF D4 FF",
                            "params2": "23 FF FF FF",
                            "posx": -1887.137451171875,
                            "posy": 1.0085309743881226,
                            "posz": 1469.1878662109375,
                            "anglex": 0,
                            "angley": 32768,
                            "anglez": 0,
                            "id": "04 3A",
                            "name": "ESf4"
                        },
                        {
                            "params1": "FF FF FF F0",
                            "params2": "04 FF FF FF",
                            "posx": -1260.0810546875,
                            "posy": -67.456298828125,
                            "posz": -1867.2623291015625,
                            "anglex": 0,
                            "angley": 16384,
                            "anglez": 0,
                            "id": "00 3B",
                            "name": "ESf"
                        },
                        {
                            "params1": "FF FF FF F0",
                            "params2": "04 FF FF FF",
                            "posx": -2368.767333984375,
                            "posy": -4.105642795562744,
                            "posz": -1648.8265380859375,
                            "anglex": 0,
                            "angley": 16384,
                            "anglez": 0,
                            "id": "00 3C",
                            "name": "ESf"
                        }
                    ]
                },
                "l2": {},
                "l3": {},
                "l4": {},
                "l5": {
                    "OBJN": [
                        "V_Clip",
                        "saveObj",
                        "WarpObj",
                        "ScChang",
                        "ClrWall"
                    ],
                    "ARCN": [
                        "PLSwordStick",
                        "InvisibleWall",
                        "SirenEntrance",
                        "PLHarpPlay"
                    ],
                    "OBJS": [
                        {
                            "params1": "FF 03 02 47",
                            "params2": "FF 5F FF FF",
                            "posx": -317.74249267578125,
                            "posy": 0.0,
                            "posz": 2630.0,
                            "anglex": 65535,
                            "angley": 16384,
                            "anglez": 65535,
                            "id": "FC 28",
                            "name": "saveObj",
                            "extra_info": {
                                "scenefid": 71,
                                "tosky_scen_link": 3,
                                "name_id": 255,
                                "subtype": "dungeon",
                                "name": "Bird Statue",
                                "scenef": "scene flag: 0x9 80"
                            }
                        }
                    ],
                    "OBJ ": [
                        {
                            "params1": "FF 02 1D 1C",
                            "params2": "FF 7F FF FF",
                            "posx": 1002.3543090820312,
                            "posy": 0.0,
                            "posz": 2586.96484375,
                            "anglex": 65527,
                            "angley": 0,
                            "anglez": 0,
                            "id": "FC 29",
                            "name": "WarpObj",
                            "extra_info": {
                                "scen_link": 2,
                                "trigscenefid": 29,
                                "untrigscenefid": 28,
                                "trigscenef": "scene flag: 0x2 20",
                                "untrigscenef": "scene flag: 0x2 10"
                            }
                        }
                    ],
                    "SOBJ": [
                        {
                            "params1": "FF FF F0 FF",
                            "params2": "FF FF FF FF",
                            "posx": -325.0,
                            "posy": 0.0,
                            "posz": 2687.0,
                            "sizex": 1.0,
                            "sizey": 3.0,
                            "sizez": 1.0,
                            "anglex": 0,
                            "angley": 0,
                            "anglez": 0,
                            "id": "FC 2A",
                            "name": "ClrWall"
                        },
                        {
                            "params1": "FF FF F0 FF",
                            "params2": "FF FF FF FF",
                            "posx": -325.0,
                            "posy": 0.0,
                            "posz": 2573.0,
                            "sizex": 1.0,
                            "sizey": 3.0,
                            "sizez": 1.0,
                            "anglex": 0,
                            "angley": 32768,
                            "anglez": 0,
                            "id": "FC 2B",
                            "name": "ClrWall"
                        }
                    ],
                    "STAG": [
                        {
                            "params1": "FF FF F1 C2",
                            "params2": "FF FF FF FF",
                            "posx": 1580.8870849609375,
                            "posy": -100.0,
                            "posz": 1205.0870361328125,
                            "sizex": 1500.0,
                            "sizey": 600.0,
                            "sizez": 400.0,
                            "anglex": 0,
                            "angley": 0,
                            "anglez": 0,
                            "id": "FC 2C",
                            "name": "V_Clip"
                        },
                        {
                            "params1": "60 FF FF 02",
                            "params2": "FF 5F FF FF",
                            "posx": 265.8437805175781,
                            "posy": -100.0,
                            "posz": 1703.998779296875,
                            "sizex": 800.0,
                            "sizey": 500.0,
                            "sizez": 800.0,
                            "anglex": 59391,
                            "angley": 0,
                            "anglez": 65535,
                            "id": "FC 2D",
                            "name": "ScChang",
                            "extra_info": {
                                "scen_link": 2,
                                "trigscenefid": 96,
                                "trigstoryfid": 2047,
                                "untrigstoryfid": 2047,
                                "trigscenef": "scene flag: 0xD 01",
                                "trigstoryf": "-",
                                "untrigstoryf": "-"
                            }
                        }
                    ]
                },
                "l6": {},
                "l7": {},
                "l8": {},
                "l9": {},
                "l10": {},
                "l11": {},
                "l12": {},
                "l13": {},
                "l14": {},
                "l15": {},
                "l16": {},
                "l17": {},
                "l18": {},
                "l19": {},
                "l20": {},
                "l21": {},
                "l22": {},
                "l23": {},
                "l24": {},
                "l25": {},
                "l26": {},
                "l27": {},
                "l28": {}
            }
        }
    }
}